src/__init__.py
src/cli.py
src/plotter.py
src/recorder.py
pingline-0.0.7.dist-info/METADATA
pingline-0.0.7.dist-info/WHEEL
pingline-0.0.7.dist-info/entry_points.txt
pingline-0.0.7.dist-info/license_files/LICENSE
pingline-0.0.7.dist-info/RECORD
