Metadata-Version: 2.1
Name: pingline
Version: 0.0.7
Summary: A small tool for pinging multiple hosts at once and exploring the data
Project-URL: Homepage, https://github.com/ipeterov/pingline
Project-URL: Bug Tracker, https://github.com/ipeterov/pingline/issues
Author-email: Ilia Peterov <ipeterov1@gmail.com>
License:                     GNU GENERAL PUBLIC LICENSE
Classifier: License :: OSI Approved :: MIT License
Classifier: Operating System :: Unix
Classifier: Programming Language :: Python :: 3
Requires-Python: >=3.7
Requires-Dist: click==8.1.3
Requires-Dist: matplotlib==3.5.2
Requires-Dist: pandas==1.4.3
